setup.py
oleg_flask_sessions.egg-info/PKG-INFO
oleg_flask_sessions.egg-info/SOURCES.txt
oleg_flask_sessions.egg-info/dependency_links.txt
oleg_flask_sessions.egg-info/not-zip-safe
oleg_flask_sessions.egg-info/requires.txt
oleg_flask_sessions.egg-info/top_level.txt
olegsessions/__init__.py
olegsessions/olegsessions.py