Metadata-Version: 1.0
Name: oleg-flask-sessions
Version: 0.2.3
Summary: Oleg DB backed sessions for Flask
Home-page: https://github.com/infoforcefeed/OlegDBFlaskSessions
Author: Quinlan Pfiffer
Author-email: qpfiffer@gmail.com
License: BSD
Keywords: OlegDB,Flask
Platform: UNKNOWN
